mlstfest/__init__.py
mlstfest/build_command.py
mlstfest/main.py
mlstfest/rest_auth.pl
mlstfest/utils.py
mlstfest-0.3.1.dist-info/entry_points.txt
mlstfest-0.3.1.dist-info/LICENSE
mlstfest-0.3.1.dist-info/WHEEL
mlstfest-0.3.1.dist-info/METADATA
mlstfest-0.3.1.dist-info/RECORD
