Metadata-Version: 2.1
Name: mlstfest
Version: 0.3.1
Summary: mlstfest can assign a strain type to novel microbial WGS data
Author: henningonsbring
Author-email: henning.onsbring@scilifelab.se
Requires-Python: >=3.9,<4.0
Classifier: Programming Language :: Python :: 3
Classifier: Programming Language :: Python :: 3.10
Classifier: Programming Language :: Python :: 3.9
Requires-Dist: pandas (>=1.4.3,<2.0.0)
Requires-Dist: typer (>=0.4.2,<0.5.0)
